{
  "$schema": "https://schema.management.azure.com/schemas/2015-01-01/deploymentTemplate.json#",
  "contentVersion": "1.0.0.0",
  "parameters": {
    "storageAccountName": {
      "type": "string",
      "defaultValue": "pocaccount9458",
      "metadata": {
        "description": "Specifies the name of the Azure Storage account."
      }
    },
    "containerPrefix": {
      "type": "string",
      "defaultValue": "logs",
      "metadata": {
        "description": "Specifies the prefix of the blob container names."
      }
    },
    "location": {
      "type": "string",
      "defaultValue": "[resourceGroup().location]",
      "metadata": {
        "description": "Specifies the location in which the Azure Storage resources should be deployed."
      }
    },
    "containerNameArray": {
      "type": "array",
      "defaultValue": [ "xmlcache", "documents" ],
      "metadata": {
        "description": "Specifies the location in which the Azure Storage resources should be deployed."
      }
    },
    "containerNameArray2": {
      "type": "array",
      "defaultValue": [ "xmlcache" ],
      "metadata": {
        "description": "Specifies the location in which the Azure Storage resources should be deployed."
      }
    }
  },
  "resources": [
    {
      "type": "Microsoft.Storage/storageAccounts",
      "apiVersion": "2018-07-01",
      "name": "[parameters('storageAccountName')]",
      "location": "[parameters('location')]",
      "kind": "StorageV2",
      "sku": {
        "name": "Standard_LRS",
        "tier": "Standard"
      },
      "properties": {
        "accessTier": "Hot"
      }
    },
    {
      "condition": "[equals(parameters('location'),'West Europe')]",
      "type": "Microsoft.Storage/storageAccounts/blobServices/containers",
      "apiVersion": "2018-07-01",
      "name": "[concat(parameters('storageAccountName'), '/default/','dev-',parameters('containerNameArray')[copyIndex()],'we-sa')]",
      "dependsOn": [
        "[resourceId('Microsoft.Storage/storageAccounts', parameters('storageAccountName'))]"
      ],
      "copy": {
        "count": "[length(parameters('containerNameArray'))]",
        "name": "containerCopy"
      }
    },
    {
      "condition": "[equals(parameters('location'),'West US 2')]",
      "type": "Microsoft.Storage/storageAccounts/blobServices/containers",
      "apiVersion": "2018-07-01",
      "name": "[concat(parameters('storageAccountName'), '/default/','dev-',parameters('containerNameArray2')[copyIndex()],'wus-sa')]",
      "dependsOn": [
        "[resourceId('Microsoft.Storage/storageAccounts', parameters('storageAccountName'))]"
      ],
      "copy": {
        "count": "[length(parameters('containerNameArray2'))]",
        "name": "containerCopy"
      }
    }
  ]
}